acrome_joint/Slave_Device.py
acrome_joint/__init__.py
acrome_joint/joint.py
acrome_joint/serial_port.py
gui/__init__.py
gui/joint_device.py
gui/limits.py
gui/main.py
gui/ramp_trajectory.py
joint_python_library-0.0.6.dist-info/licenses/LICENSE
joint_python_library-0.0.6.dist-info/METADATA
joint_python_library-0.0.6.dist-info/WHEEL
joint_python_library-0.0.6.dist-info/entry_points.txt
joint_python_library-0.0.6.dist-info/top_level.txt
joint_python_library-0.0.6.dist-info/RECORD
